README.md
setup.py
aninja/__init__.py
aninja/browser.py
aninja/cookies.py
aninja/http.py
aninja/utils.py
aninja.egg-info/PKG-INFO
aninja.egg-info/SOURCES.txt
aninja.egg-info/dependency_links.txt
aninja.egg-info/requires.txt
aninja.egg-info/top_level.txt